pyhud/__init__.py
hud_pysdk-0.0.0a0.dist-info/METADATA
hud_pysdk-0.0.0a0.dist-info/WHEEL
hud_pysdk-0.0.0a0.dist-info/top_level.txt
hud_pysdk-0.0.0a0.dist-info/RECORD
